dotatools/__init__.py
dotatools/hero.py
dotatools/match.py
dotatools/user.py
dotatools-0.1.dist-info/DESCRIPTION.rst
dotatools-0.1.dist-info/METADATA
dotatools-0.1.dist-info/RECORD
dotatools-0.1.dist-info/WHEEL
dotatools-0.1.dist-info/metadata.json
dotatools-0.1.dist-info/top_level.txt
